Workbook

Sheet EMPIEZA AQUÍ 👋
B2: TABLERO PRIMERAS 10 VENTAS
B3: Herramienta 14 · Aquí ves qué pasó después de contactar y cuántas ventas llevas. Incluye la Ficha de Pedido (Herramienta 13).
B5: CÓMO USARLO
B6: 1. Trae tus prospectos del Radar (sin escribirlos otra vez). | C6: En tu Radar selecciona las columnas B a E de MI RADAR (Nombre, Tipo, Zona, Canal), cópialas y pégalas en la columna B de la pestaña TABLERO.
B7: 2. Anota qué pasa con cada persona. | C7: En la pestaña TABLERO elige Sí o No en las columnas Contactado, Respondió, Pedido y Entregado.
B8: 3. Cuando haya un pedido, escribe el monto. | C8: Si quieres, anota también el costo: la ganancia se calcula sola.
B9: 4. Mira MIS 10 VENTAS. | C9: Cada pedido llena una casilla. No hay que hacer nada más.
B10: 5. Para cada pedido, usa la FICHA DE PEDIDO. | C10: Duplica la pestaña (clic derecho → Mover o copiar / Duplicar) y completa una ficha por pedido.
B12: RADAR Y TABLERO: NO SON LO MISMO
B13: RADAR: a quién puedes contactar y cuál es tu próxima acción. | D13: TABLERO: qué pasó después de contactar y cuántas ventas estás consiguiendo.
B16: COLORES
B17: Rosado: lo escribes o eliges tú
B18: Durazno: se calcula solo (no lo toques)
B20: Este Tablero no promete ventas: solo te ayuda a ver tu avance. Registra únicamente pedidos y montos reales. Contactar no significa presionar.

Sheet MIS 10 VENTAS
B1: MIS PRIMERAS 10 VENTAS
B2: Cada pedido que marcas con “Sí” en TABLERO llena una casilla.
B4: ="Llevas "&B13&" de 10 ventas"
B5: ="Progreso: "&REPT("█",ROUND(MIN(1,B13/10)*20,0))&REPT("░",20-ROUND(MIN(1,B13/10)*20,0))
B7: 1 | C7: 2 | D7: 3 | E7: 4 | F7: 5 | G7: 6 | H7: 7 | I7: 8 | J7: 9 | K7: 10
B8: =IF($B$13>=1,"✔","○") | C8: =IF($B$13>=2,"✔","○") | D8: =IF($B$13>=3,"✔","○") | E8: =IF($B$13>=4,"✔","○") | F8: =IF($B$13>=5,"✔","○") | G8: =IF($B$13>=6,"✔","○") | H8: =IF($B$13>=7,"✔","○") | I8: =IF($B$13>=8,"✔","○") | J8: =IF($B$13>=9,"✔","○") | K8: =IF($B$13>=10,"✔","○")
B9: Venta | C9: Venta | D9: Venta | E9: Venta | F9: Venta | G9: Venta | H9: Venta | I9: Venta | J9: Venta | K9: Venta
B11: TUS CIFRAS
B12: =COUNTA(TABLERO!$B$9:$B$68) | C12: Prospectos cargados
B13: =COUNTIF(TABLERO!$H$9:$H$68,"Sí") | C13: Ventas (pedidos con “Sí”)
B14: =COUNTIF(TABLERO!$L$9:$L$68,"Sí") | C14: Pedidos entregados
B15: =COUNTIF(TABLERO!$F$9:$F$68,"Sí") | C15: Contactados
B16: =COUNTIF(TABLERO!$G$9:$G$68,"Sí") | C16: Respondieron
B17: =SUM(TABLERO!$I$9:$I$68) | C17: Total vendido
B18: =SUM(TABLERO!$K$9:$K$68) | C18: Ganancia registrada
B20: La ganancia solo suma los pedidos en los que anotaste monto y costo. Los cuadros se actualizan solos.

Sheet TABLERO
A1: TABLERO · qué pasó después de contactar
A2: Pega tus prospectos del Radar en las columnas B a E (Nombre, Tipo, Zona, Canal). Después elige Sí o No en las demás columnas.
A4: Copiar desde el Radar → selecciona B a E en MI RADAR (Nombre, Tipo, Zona, Canal posible) → pega en B9 de esta hoja. Las columnas coinciden a propósito.
A6: ="Ventas: "&COUNTIF(H9:H68,"Sí")&" de 10 · Total vendido: "&TEXT(SUM(I9:I68),"#,##0.00")
A8: N.º | B8: Nombre / negocio | C8: Tipo de prospecto | D8: Zona | E8: Canal | F8: ¿Contactado? | G8: ¿Respondió? | H8: ¿Hizo pedido? | I8: Monto del pedido | J8: Costo (opcional) | K8: Ganancia (auto) | L8: ¿Entregado? | M8: Seguimiento (qué sigue y cuándo) | N8: Etapa (auto)
A9: 1 | K9: =IF(AND(ISNUMBER(I9),ISNUMBER(J9)),I9-J9,"") | N9: =IF(B9="","",IF(L9="Sí","Entregado",IF(H9="Sí","Pedido",IF(G9="Sí","Respondió",IF(F9="Sí","Contactado","Por contactar")))))
A10: 2 | K10: =IF(AND(ISNUMBER(I10),ISNUMBER(J10)),I10-J10,"") | N10: =IF(B10="","",IF(L10="Sí","Entregado",IF(H10="Sí","Pedido",IF(G10="Sí","Respondió",IF(F10="Sí","Contactado","Por contactar")))))
A11: 3 | K11: =IF(AND(ISNUMBER(I11),ISNUMBER(J11)),I11-J11,"") | N11: =IF(B11="","",IF(L11="Sí","Entregado",IF(H11="Sí","Pedido",IF(G11="Sí","Respondió",IF(F11="Sí","Contactado","Por contactar")))))
A12: 4 | K12: =IF(AND(ISNUMBER(I12),ISNUMBER(J12)),I12-J12,"") | N12: =IF(B12="","",IF(L12="Sí","Entregado",IF(H12="Sí","Pedido",IF(G12="Sí","Respondió",IF(F12="Sí","Contactado","Por contactar")))))
A13: 5 | K13: =IF(AND(ISNUMBER(I13),ISNUMBER(J13)),I13-J13,"") | N13: =IF(B13="","",IF(L13="Sí","Entregado",IF(H13="Sí","Pedido",IF(G13="Sí","Respondió",IF(F13="Sí","Contactado","Por contactar")))))
A14: 6 | K14: =IF(AND(ISNUMBER(I14),ISNUMBER(J14)),I14-J14,"") | N14: =IF(B14="","",IF(L14="Sí","Entregado",IF(H14="Sí","Pedido",IF(G14="Sí","Respondió",IF(F14="Sí","Contactado","Por contactar")))))
A15: 7 | K15: =IF(AND(ISNUMBER(I15),ISNUMBER(J15)),I15-J15,"") | N15: =IF(B15="","",IF(L15="Sí","Entregado",IF(H15="Sí","Pedido",IF(G15="Sí","Respondió",IF(F15="Sí","Contactado","Por contactar")))))
A16: 8 | K16: =IF(AND(ISNUMBER(I16),ISNUMBER(J16)),I16-J16,"") | N16: =IF(B16="","",IF(L16="Sí","Entregado",IF(H16="Sí","Pedido",IF(G16="Sí","Respondió",IF(F16="Sí","Contactado","Por contactar")))))
A17: 9 | K17: =IF(AND(ISNUMBER(I17),ISNUMBER(J17)),I17-J17,"") | N17: =IF(B17="","",IF(L17="Sí","Entregado",IF(H17="Sí","Pedido",IF(G17="Sí","Respondió",IF(F17="Sí","Contactado","Por contactar")))))
A18: 10 | K18: =IF(AND(ISNUMBER(I18),ISNUMBER(J18)),I18-J18,"") | N18: =IF(B18="","",IF(L18="Sí","Entregado",IF(H18="Sí","Pedido",IF(G18="Sí","Respondió",IF(F18="Sí","Contactado","Por contactar")))))
A19: 11 | K19: =IF(AND(ISNUMBER(I19),ISNUMBER(J19)),I19-J19,"") | N19: =IF(B19="","",IF(L19="Sí","Entregado",IF(H19="Sí","Pedido",IF(G19="Sí","Respondió",IF(F19="Sí","Contactado","Por contactar")))))
A20: 12 | K20: =IF(AND(ISNUMBER(I20),ISNUMBER(J20)),I20-J20,"") | N20: =IF(B20="","",IF(L20="Sí","Entregado",IF(H20="Sí","Pedido",IF(G20="Sí","Respondió",IF(F20="Sí","Contactado","Por contactar")))))
... A68: 60 | K68: =IF(AND(ISNUMBER(I68),ISNUMBER(J68)),I68-J68,"") | N68: =IF(B68="","",IF(L68="Sí","Entregado",IF(H68="Sí","Pedido",IF(G68="Sí","Respondió",IF(F68="Sí","Contactado","Por contactar")))))

Sheet FICHA DE PEDIDO
B1: FICHA DE PEDIDO
B2: Herramienta 13 · Una ficha por pedido. Duplica esta pestaña (clic derecho → Mover o copiar / Duplicar) o imprímela.
B4: Cliente | D4: Contacto (WhatsApp, teléfono…)
B5: Producto | D5: Cantidad
B6: Personalización (si corresponde) | D6: Fecha de entrega
B7: Hora | D7: Entrega o retiro
B8: Zona o dirección (si corresponde) | D8: Total
B9: Estado del pago
B11: Notas
B17: Antes de dar el pedido por cerrado, confirma: producto y cantidad · fecha y hora · entrega o retiro · total · forma de pago. Cuando esté claro, anota en TABLERO: ¿Hizo pedido? = Sí y el monto. El anticipo o pago previo es una política que tú decides y comunicas antes de aceptar el pedido.
